multiMotif/__init__.py
multiMotif/main.py
multiMotif-1.2.6.dist-info/LICENSE
multiMotif-1.2.6.dist-info/METADATA
multiMotif-1.2.6.dist-info/WHEEL
multiMotif-1.2.6.dist-info/entry_points.txt
multiMotif-1.2.6.dist-info/top_level.txt
multiMotif-1.2.6.dist-info/RECORD
