Metadata-Version: 2.1
Name: multiMotif
Version: 1.2.6
Summary: A Computational Tool for Variable Motif scanning and Sequence-based Relative Position Visualization of Search Results in Sequences.
Home-page: https://github.com/SainanLuo/multiMotif
Author: Sainan Luo
License-File: LICENSE
Requires-Dist: biopython>=1.78
Requires-Dist: matplotlib>=3.3
Requires-Dist: numpy>=1.19
Requires-Dist: pandas>=1.1
Requires-Dist: plotly>=5.18.0
Requires-Dist: kaleido>=0.2.1
